webknossos/__init__.py
webknossos/py.typed
webknossos/ssl_context.py
webknossos/utils.py
webknossos/version.py
webknossos/_nml/__init__.py
webknossos/_nml/branchpoint.py
webknossos/_nml/comment.py
webknossos/_nml/edge.py
webknossos/_nml/group.py
webknossos/_nml/meta.py
webknossos/_nml/metadata_entry.py
webknossos/_nml/nml.py
webknossos/_nml/node.py
webknossos/_nml/parameters.py
webknossos/_nml/segment.py
webknossos/_nml/tree.py
webknossos/_nml/utils.py
webknossos/_nml/volume.py
webknossos/administration/__init__.py
webknossos/administration/project.py
webknossos/administration/task.py
webknossos/administration/team.py
webknossos/administration/user.py
webknossos/annotation/__init__.py
webknossos/annotation/_nml_conversion.py
webknossos/annotation/annotation.py
webknossos/annotation/annotation_info.py
webknossos/annotation/volume_layer.py
webknossos/cli/__init__.py
webknossos/cli/_utils.py
webknossos/cli/check_equality.py
webknossos/cli/compress.py
webknossos/cli/convert.py
webknossos/cli/convert_knossos.py
webknossos/cli/convert_raw.py
webknossos/cli/convert_zarr.py
webknossos/cli/copy_dataset.py
webknossos/cli/download.py
webknossos/cli/downsample.py
webknossos/cli/export_as_tiff.py
webknossos/cli/main.py
webknossos/cli/merge_fallback.py
webknossos/cli/upload.py
webknossos/cli/upsample.py
webknossos/client/__init__.py
webknossos/client/_defaults.py
webknossos/client/_download_dataset.py
webknossos/client/_resolve_short_link.py
webknossos/client/_upload_dataset.py
webknossos/client/context.py
webknossos/client/_resumable/__init__.py
webknossos/client/_resumable/chunk.py
webknossos/client/_resumable/core.py
webknossos/client/_resumable/file.py
webknossos/client/_resumable/util.py
webknossos/client/api_client/__init__.py
webknossos/client/api_client/_abstract_api_client.py
webknossos/client/api_client/_serialization.py
webknossos/client/api_client/datastore_api_client.py
webknossos/client/api_client/errors.py
webknossos/client/api_client/models.py
webknossos-3.1.3.dist-info/METADATA
webknossos-3.1.3.dist-info/WHEEL
webknossos-3.1.3.dist-info/entry_points.txt
webknossos-3.1.3.dist-info/top_level.txt
webknossos-3.1.3.dist-info/RECORD
