Metadata-Version: 2.4
Name: webknossos
Version: 3.1.3
Summary: Python API for working with WEBKNOSSOS datasets, annotations, and for WEBKNOSSOS server interaction.
Author-email: scalable minds <hello@scalableminds.com>
License: AGPL-3.0
Project-URL: Homepage, https://docs.webknossos.org/webknossos-py
Project-URL: Repository, https://github.com/scalableminds/webknossos-libs
Project-URL: Documentation, https://docs.webknossos.org
Project-URL: Changelog, https://github.com/scalableminds/webknossos-libs/blob/master/webknossos/Changelog.md
Classifier: Intended Audience :: Developers
Classifier: Intended Audience :: Education
Classifier: Intended Audience :: Healthcare Industry
Classifier: Intended Audience :: Information Technology
Classifier: Intended Audience :: Science/Research
Classifier: Operating System :: OS Independent
Classifier: Topic :: Education
Classifier: Topic :: Multimedia :: Graphics
Classifier: Topic :: Scientific/Engineering
Classifier: Topic :: Scientific/Engineering :: Bio-Informatics
Classifier: Topic :: Scientific/Engineering :: Image Processing
Classifier: Topic :: Scientific/Engineering :: Information Analysis
Classifier: Topic :: Scientific/Engineering :: Medical Science Apps.
Classifier: Topic :: Scientific/Engineering :: Visualization
Classifier: Topic :: Software Development :: Libraries
Classifier: Typing :: Typed
Classifier: Programming Language :: Python :: 3.10
Classifier: Programming Language :: Python :: 3.11
Classifier: Programming Language :: Python :: 3.12
Classifier: Programming Language :: Python :: 3.13
Requires-Python: <3.14,>=3.10
Requires-Dist: aiohttp~=3.10.5
Requires-Dist: attrs>=22.0.0
Requires-Dist: boltons>=21.0.0
Requires-Dist: cattrs>=22.0.0
Requires-Dist: certifi>=2023
Requires-Dist: click<8.2.0
Requires-Dist: cluster-tools==3.1.3
Requires-Dist: httpx~=0.27.0
Requires-Dist: loxun~=2.0.0
Requires-Dist: natsort~=8.4.0
Requires-Dist: networkx~=3.2.1
Requires-Dist: numpy<3.0.0,>=2.0.0
Requires-Dist: pims~=0.7.0
Requires-Dist: protobuf<7,>=3.12.0
Requires-Dist: google-api-python-client>=2.0.0
Requires-Dist: psutil~=6.0.0
Requires-Dist: python-dateutil>=2.9.0
Requires-Dist: python-dotenv~=1.0.1
Requires-Dist: rich~=13.8.0
Requires-Dist: s3fs>=2024.6.1
Requires-Dist: scipy>=1.13
Requires-Dist: tensorstore==0.1.76; sys_platform == "win32"
Requires-Dist: tensorstore~=0.1.78; sys_platform != "win32"
Requires-Dist: typer~=0.12.5
Requires-Dist: typing-extensions~=4.0
Requires-Dist: universal-pathlib~=0.2
Requires-Dist: wkw==1.1.24
Requires-Dist: zipp~=3.5.0
Provides-Extra: tifffile
Requires-Dist: tifffile<2025.5.21,>=2024.8.24; extra == "tifffile"
Provides-Extra: imagecodecs
Requires-Dist: imagecodecs>=2021.11.20; extra == "imagecodecs"
Provides-Extra: bioformats
Requires-Dist: JPype1~=1.5.0; extra == "bioformats"
Provides-Extra: czi
Requires-Dist: pylibCZIrw==5.1.1; extra == "czi"
Provides-Extra: examples
Requires-Dist: fastremap~=1.15.0; extra == "examples"
Requires-Dist: pandas~=2.2.0; extra == "examples"
Requires-Dist: pooch~=1.5.2; extra == "examples"
Requires-Dist: s3fs>=2023.9.0; extra == "examples"
Requires-Dist: tabulate>=0.9.0; extra == "examples"
Requires-Dist: scikit-learn~=1.5.1; extra == "examples"
Requires-Dist: scikit-image~=0.25.0; extra == "examples"
Provides-Extra: all
Requires-Dist: webknossos[tifffile]; extra == "all"
Requires-Dist: webknossos[imagecodecs]; extra == "all"
Requires-Dist: webknossos[bioformats]; extra == "all"
Requires-Dist: webknossos[czi]; extra == "all"
Requires-Dist: webknossos[examples]; extra == "all"
